README.md
setup.cfg
setup.py
histocartography/__init__.py
histocartography/pipeline.py
histocartography.egg-info/PKG-INFO
histocartography.egg-info/SOURCES.txt
histocartography.egg-info/dependency_links.txt
histocartography.egg-info/not-zip-safe
histocartography.egg-info/requires.txt
histocartography.egg-info/top_level.txt
histocartography/interpretability/__init__.py
histocartography/interpretability/base_explainer.py
histocartography/interpretability/grad_cam.py
histocartography/interpretability/graph_pruning_explainer.py
histocartography/interpretability/lrp_gnn_explainer.py
histocartography/metrics/__init__.py
histocartography/metrics/metrics.py
histocartography/ml/__init__.py
histocartography/ml/layers/__init__.py
histocartography/ml/layers/constants.py
histocartography/ml/layers/dense_gin_layer.py
histocartography/ml/layers/gin_layer.py
histocartography/ml/layers/mlp.py
histocartography/ml/layers/multi_layer_gnn.py
histocartography/ml/layers/pna_layer.py
histocartography/ml/models/__init__.py
histocartography/ml/models/base_model.py
histocartography/ml/models/cell_graph_model.py
histocartography/ml/models/hact_model.py
histocartography/ml/models/hovernet.py
histocartography/ml/models/tissue_graph_model.py
histocartography/ml/models/zoo.py
histocartography/preprocessing/__init__.py
histocartography/preprocessing/assignment_matrix.py
histocartography/preprocessing/feature_extraction.py
histocartography/preprocessing/graph_builders.py
histocartography/preprocessing/io.py
histocartography/preprocessing/nuclei_concept_extraction.py
histocartography/preprocessing/nuclei_extraction.py
histocartography/preprocessing/stain_normalizers.py
histocartography/preprocessing/stats.py
histocartography/preprocessing/superpixel.py
histocartography/preprocessing/tissue_mask.py
histocartography/preprocessing/utils.py
histocartography/utils/__init__.py
histocartography/utils/draw_utils.py
histocartography/utils/graph.py
histocartography/utils/image.py
histocartography/utils/io.py
histocartography/utils/torch.py
histocartography/visualization/__init__.py
histocartography/visualization/visualization.py
test/__init__.py
test/interpretability/__init__.py
test/interpretability/test_gnnexplainer.py
