Metadata-Version: 2.1
Name: histocartography
Version: 0.2.1
Summary: Installable histocartography package.
Home-page: https://github.com/histocartography/histocartography
Author: Guillaume Jaume, Pushpak Pati, Antonio Foncubierta Rodríguez
Author-email: guillaume.jaume2@gmail.com, pushpak.nitrkl@gmail.com, antonio.foncubierta@gmail.com
License: UNKNOWN
Download-URL: https://github.com/histocartography/histocartography/archive/refs/tags/v0.2.1.tar.gz
Platform: UNKNOWN
Classifier: Programming Language :: Python :: 3
Classifier: License :: OSI Approved :: GNU Affero General Public License v3
Classifier: Operating System :: OS Independent
